{
  "snippet-format": "snippet",
  "total": 1369555,
  "start": 1,
  "page-length": 10,
  "selected": "include",
  "results": [],
  "facets": {
    "WordCloud": {
      "type": "xs:string",
      "facetValues": [{
        "name": "ENGINE",
        "count": 105445,
        "value": "ENGINE"
      }, {
        "name": "FAILED",
        "count": 93673,
        "value": "FAILED"
      }, {
        "name": "LIGHT",
        "count": 88209,
        "value": "LIGHT"
      }, {
        "name": "BRAKE",
        "count": 86311,
        "value": "BRAKE"
      }, {
        "name": "SIDE",
        "count": 83392,
        "value": "SIDE"
      }, {
        "name": "CONSUMER",
        "count": 83159,
        "value": "CONSUMER"
      }, {
        "name": "REAR",
        "count": 81995,
        "value": "REAR"
      }, {
        "name": "FRONT",
        "count": 80650,
        "value": "FRONT"
      }, {
        "name": "STEERING",
        "count": 72696,
        "value": "STEERING"
      }, {
        "name": "REPLACED",
        "count": 72484,
        "value": "REPLACED"
      }, {
        "name": "CONTROL",
        "count": 70612,
        "value": "CONTROL"
      }, {
        "name": "AIR",
        "count": 64284,
        "value": "AIR"
      }, {
        "name": "BRAKES",
        "count": 63843,
        "value": "BRAKES"
      }, {
        "name": "TIRE",
        "count": 61435,
        "value": "TIRE"
      }, {
        "name": "TRANSMISSION",
        "count": 59415,
        "value": "TRANSMISSION"
      }, {
        "name": "SYSTEM",
        "count": 58113,
        "value": "SYSTEM"
      }, {
        "name": "SEAT",
        "count": 57034,
        "value": "SEAT"
      }, {
        "name": "FUEL",
        "count": 56200,
        "value": "FUEL"
      }, {
        "name": "POWER",
        "count": 52896,
        "value": "POWER"
      }, {
        "name": "DOOR",
        "count": 50194,
        "value": "DOOR"
      }]
    }
  },
  "query": {
    "and-query": [{
      "annotation": [{
        "operator-ref": "results",
        "state-ref": "compact"
      }]
    }]
  },
  "metrics": {
    "query-resolution-time": "PT0.057791S",
    "facet-resolution-time": "PT0.208874S",
    "snippet-resolution-time": "PT0.005119S",
    "metadata-resolution-time": "PT0.013723S",
    "extract-resolution-time": "PT0.001884S",
    "total-time": "PT0.295157S"
  }
}
